{
    "display": {
        "title": {
            "text": "Truly Magical"
        },
        "description": {
            "text": "Gain magical powers"
        },
        "icon": {
            "item": "minecraft:carrot_on_a_stick",
            "nbt": "{CustomModelData:1}"
        },
        "frame": "goal",
        "show_toast": true,
        "announce_to_chat": true,
        "hidden": false,
        "background": "minecraft:textures/block/bookshelf.png"
    },
    "criteria": {
        "obtain": {
            "trigger": "minecraft:inventory_changed",
            "conditions": {
                "items": [
                    {
                        "nbt": "{CustomItem:1}"
                    }
                ]
            }
        }
    },
    "rewards": {
        "experience": 100
    }
}